Metadata-Version: 2.1
Name: odoo-addon-l10n_br_portal
Version: 16.0.2.1.1
Requires-Python: >=3.10
Requires-Dist: odoo-addon-l10n_br_zip>=16.0dev,<16.1dev
Requires-Dist: odoo>=16.0a,<16.1dev
Summary: Campos Brasileiros no Portal
Home-page: https://github.com/OCA/l10n-brazil
License: AGPL-3
Author: KMEE,Odoo Community Association (OCA)
Author-email: support@odoo-community.org
Classifier: Programming Language :: Python
Classifier: Framework :: Odoo
Classifier: Framework :: Odoo :: 16.0
Classifier: License :: OSI Approved :: GNU Affero General Public License v3
Classifier: Development Status :: 5 - Production/Stable
